tree_sitter_rql/__init__.py
tree_sitter_rql/__init__.pyi
tree_sitter_rql/_binding.abi3.so
tree_sitter_rql/binding.c
tree_sitter_rql/queries/highlights.scm
tree_sitter_rql-0.1.4.dist-info/METADATA
tree_sitter_rql-0.1.4.dist-info/WHEEL
tree_sitter_rql-0.1.4.dist-info/top_level.txt
tree_sitter_rql-0.1.4.dist-info/RECORD
tree_sitter_rql-0.1.4.dist-info/licenses/LICENSE.txt
