Metadata-Version: 2.4
Name: tree-sitter-rql
Version: 0.1.4
Summary: RQL grammar for tree-sitter
Author: SoftwareOne AG
License:                                  Apache License
Project-URL: Homepage, https://github.com/softwareone-platform/tree-sitter-rql
Keywords: incremental,parsing,tree-sitter,rql
Classifier: Intended Audience :: Developers
Classifier: License :: OSI Approved :: Apache Software License
Classifier: Topic :: Software Development :: Compilers
Classifier: Topic :: Text Processing :: Linguistic
Classifier: Typing :: Typed
Requires-Python: <4,>=3.9
License-File: LICENSE.txt
Provides-Extra: core
Requires-Dist: tree-sitter~=0.22; extra == "core"
Dynamic: license-file
